scalesafe/__init__.py
scalesafe/benchmarking.py
scalesafe/claude.py
scalesafe/exceptions.py
scalesafe/generic.py
scalesafe/langchain.py
scalesafe/onprem.py
scalesafe/openai.py
tests/__init__.py
tests/example_usage.py
tests/test_generic_monitor.py
scalesafe-0.0.3.dist-info/LICENSE
scalesafe-0.0.3.dist-info/METADATA
scalesafe-0.0.3.dist-info/WHEEL
scalesafe-0.0.3.dist-info/top_level.txt
scalesafe-0.0.3.dist-info/RECORD
