Metadata-Version: 2.1
Name: scalesafe
Version: 0.0.3
Summary: ScaleSafe Monitoring Engine: Toolkit for integrating monitoring into AI systems for compliance and safety.
Home-page: https://scalesafe.ai
Author: Tobin South
Author-email: tsouth@mit.edu
License: MIT
Classifier: Development Status :: 3 - Alpha
Classifier: Intended Audience :: Developers
Classifier: License :: OSI Approved :: MIT License
Classifier: Programming Language :: Python :: 3
Classifier: Programming Language :: Python :: 3.10
Classifier: Operating System :: OS Independent
Requires-Python: >=3.8
License-File: LICENSE
Requires-Dist: requests
Provides-Extra: dev
Requires-Dist: pytest >=6.2.5 ; extra == 'dev'
